 {
  "ret": "true",
  "data": {
    "bannerInfo": "境外当地玩乐",
    "images": [
      "https://img.alicdn.com/bao/uploaded/i4/TB1fWSyex9YBuNjy0FfTjlIsVXa_030421.jpg_640x640q30.jpg",
      "https://img.alicdn.com/bao/uploaded/i1/1911947373/TB2lXJ0CH9YBuNjy0FgXXcxcXXa_!!1911947373.jpg_640x640q30.jpg",
      "https://img.alicdn.com/bao/uploaded/i4/3362606005/TB2YLrTrASWBuNjSszdXXbeSpXa_!!3362606005.jpg_640x640q30.jpg",
      "https://img.alicdn.com/bao/uploaded/i2/3362606005/TB2PGvWrv1TBuNjy0FjXXajyXXa_!!3362606005.jpg_640x640q30.jpg",
      "https://img.alicdn.com/bao/uploaded/i1/3362606005/TB2u5oPmStYBeNjSspkXXbU8VXa_!!3362606005.jpg_640x640q30.jpg"
    ],
    "list": [{
      "title": "成人票",
      "children": [{
        "title": "上午场"
      }, {
        "title": "下午场"
      }]
    }, {
      "title": "儿童票",
      "children": [{
        "title": "上午场"
      }, {
        "title": "下午场"
      }]
    }, {
      "title": "学生票",
      "children": [{
        "title": "上午场"
      }, {
        "title": "下午场"
      }]
    }, {
      "title": "老人票",
      "children": [{
        "title": "上午场"
      }, {
        "title": "下午场"
      }]
    }, {
      "title": "特惠票",
      "children": [{
        "title": "上午场"
      }, {
        "title": "下午场"
      }]
    }]
  }
}